mqt/qcec/__init__.py
mqt/qcec/_version.py
mqt/qcec/_version.pyi
mqt/qcec/compilation_flow_profiles.py
mqt/qcec/configuration_options.py
mqt/qcec/parameterized.py
mqt/qcec/py.typed
mqt/qcec/pyqcec.cpython-313t-x86_64-linux-gnu.so
mqt/qcec/pyqcec.pyi
mqt/qcec/verify.py
mqt/qcec/verify_compilation_flow.py
mqt/qcec/_compat/__init__.py
mqt/qcec/_compat/optional.py
mqt/qcec/_compat/typing.py
mqt/qcec/profiles/qiskit_O0_noancilla.profile
mqt/qcec/profiles/qiskit_O0_recursion.profile
mqt/qcec/profiles/qiskit_O0_v-chain.profile
mqt/qcec/profiles/qiskit_O1_noancilla.profile
mqt/qcec/profiles/qiskit_O1_recursion.profile
mqt/qcec/profiles/qiskit_O1_v-chain.profile
mqt/qcec/profiles/qiskit_O2_noancilla.profile
mqt/qcec/profiles/qiskit_O2_recursion.profile
mqt/qcec/profiles/qiskit_O2_v-chain.profile
mqt/qcec/profiles/qiskit_O3_noancilla.profile
mqt/qcec/profiles/qiskit_O3_recursion.profile
mqt/qcec/profiles/qiskit_O3_v-chain.profile
mqt_qcec-3.3.0.dist-info/METADATA
mqt_qcec-3.3.0.dist-info/WHEEL
mqt_qcec-3.3.0.dist-info/RECORD
mqt_qcec-3.3.0.dist-info/licenses/LICENSE.md
