Metadata-Version: 2.4
Name: mqt.qcec
Version: 3.3.0
Summary: A tool for Quantum Circuit Equivalence Checking
Keywords: MQT,quantum-computing,design-automation,equivalence-checking,verification
Author-Email: Lukas Burgholzer <lukas.burgholzer@tum.de>, Tom Peham <tom.peham@tum.de>
License-Expression: MIT
License-File: LICENSE.md
Classifier: Topic :: Scientific/Engineering :: Electronic Design Automation (EDA)
Classifier: Intended Audience :: Science/Research
Classifier: Natural Language :: English
Classifier: Operating System :: POSIX :: Linux
Classifier: Operating System :: MacOS
Classifier: Operating System :: Microsoft :: Windows
Classifier: Programming Language :: C++
Classifier: Programming Language :: Python
Classifier: Programming Language :: Python :: 3
Classifier: Programming Language :: Python :: 3 :: Only
Classifier: Programming Language :: Python :: 3.10
Classifier: Programming Language :: Python :: 3.11
Classifier: Programming Language :: Python :: 3.12
Classifier: Programming Language :: Python :: 3.13
Classifier: Programming Language :: Python :: 3.14
Classifier: Development Status :: 5 - Production/Stable
Classifier: Typing :: Typed
Project-URL: Homepage, https://github.com/munich-quantum-toolkit/qcec
Project-URL: Documentation, https://mqt.readthedocs.io/projects/qcec
Project-URL: Issues, https://github.com/munich-quantum-toolkit/qcec/issues
Project-URL: Discussions, https://github.com/munich-quantum-toolkit/qcec/discussions
Requires-Python: >=3.10
Requires-Dist: mqt.core~=3.3.1
Requires-Dist: typing_extensions>=4.2; python_version < "3.11"
Requires-Dist: numpy>=1.22
Requires-Dist: numpy>=1.24; python_version >= "3.11"
Requires-Dist: numpy>=1.26; python_version >= "3.12"
Requires-Dist: numpy>=2.1; python_version >= "3.13"
Requires-Dist: numpy>=2.3.2; python_version >= "3.14"
Provides-Extra: qiskit
Requires-Dist: qiskit[qasm3-import]>=1.0.0; extra == "qiskit"
